CHANGES.txt
CONTRIBUTORS.txt
KNOWN_ISSUES.txt
README.txt
setup.cfg
setup.py
collective/__init__.py
collective.portlet.facet.egg-info/PKG-INFO
collective.portlet.facet.egg-info/SOURCES.txt
collective.portlet.facet.egg-info/dependency_links.txt
collective.portlet.facet.egg-info/entry_points.txt
collective.portlet.facet.egg-info/namespace_packages.txt
collective.portlet.facet.egg-info/not-zip-safe
collective.portlet.facet.egg-info/requires.txt
collective.portlet.facet.egg-info/top_level.txt
collective/portlet/__init__.py
collective/portlet/facet/__init__.py
collective/portlet/facet/build-i18n.py
collective/portlet/facet/configure.zcml
collective/portlet/facet/facetnavigation.pt
collective/portlet/facet/facetnavigation.py
collective/portlet/facet/profiles/default/metadata.xml
collective/portlet/facet/profiles/default/portlets.xml
collective/portlet/facet/tests/__init__.py
collective/portlet/facet/tests/base.py
collective/portlet/facet/tests/browser.txt
collective/portlet/facet/tests/test_doc.py
collective/portlet/facet/tests/test_portlet.py
docs/INSTALL.txt
docs/LICENSE.GPL
docs/LICENSE.txt