Metadata-Version: 1.0
Name: collective.portlet.facet
Version: 0.1a1
Summary: Facet navigation portlet
Home-page: http://plone.org/products
Author: Martin Lundwall and Robin Harms Oredsson
Author-email: robin@betahaus.net
License: GPL
Keywords: plone portlet
Platform: UNKNOWN
Classifier: Framework :: Plone
Classifier: Programming Language :: Python
Classifier: Development Status :: 3 - Alpha
Classifier: License :: OSI Approved :: GNU General Public License (GPL)
